joystick_controller/__init__.py
joystick_controller/control_assignment.py
joystick_controller-1.2.2.dist-info/DESCRIPTION.rst
joystick_controller-1.2.2.dist-info/METADATA
joystick_controller-1.2.2.dist-info/RECORD
joystick_controller-1.2.2.dist-info/WHEEL
joystick_controller-1.2.2.dist-info/metadata.json
joystick_controller-1.2.2.dist-info/top_level.txt
