Metadata-Version: 2.0
Name: joystick-controller
Version: 1.2.2
Summary: A simple library to map joystick inputs, or gamepad to a given control variable
Home-page: https://github.com/MarceloJacinto/joystick-controller
Author: MarceloJacinto
Author-email: marcelo.jacinto@tecnico.ulisboa.pt
License: MIT
Platform: Windows
Platform: Linux
Platform: Solaris
Platform: Mac OS-X
Platform: Unix
Requires-Python: >=2.7
Requires-Dist: pygame (>=2.0.3)
Requires-Dist: typing
